.gitignore
README.md
requirements.txt
setup.py
termstree/__init__.py
termstree/index.py
termstree/node.py
termstree/parser.py
termstree/tree.py
termstree/utils.py
termstree.egg-info/PKG-INFO
termstree.egg-info/SOURCES.txt
termstree.egg-info/dependency_links.txt
termstree.egg-info/requires.txt
termstree.egg-info/top_level.txt
tests/test_index.py
tests/test_node.py
tests/test_termstree.py
tests/test_termstree_parser.py
tests/test_utils.py