Metadata-Version: 2.1
Name: termstree
Version: 0.2
Summary: Library for parsing terms tree from indented text file and searching texts for the tree terms
Home-page: https://github.com/gruzovator/termstree
Author: gruzovator
Author-email: gruzovator@gmail.com
License: MIT
Keywords: labeling,classification,search,NLP
Platform: UNKNOWN
Requires-Python: >=3
